{"organe": {"@xmlns": "http://schemas.assemblee-nationale.fr/referentiel", "@xmlns:xsi": "http://www.w3.org/2001/XMLSchema-instance", "@xsi:type": "OrganeParlementaire_Type", "uid": "PO826046", "codeType": "MISINFO", "libelle": "Mission d'information sur l'enseignement sup\u00e9rieur priv\u00e9 \u00e0 but lucratif", "libelleEdition": null, "libelleAbrege": "Enseignement sup\u00e9rieur \u00e0 but lucratif", "libelleAbrev": "ENSSUPPRIV", "viMoDe": {"dateDebut": "2023-07-05", "dateAgrement": null, "dateFin": "2024-04-10"}, "organeParent": "PO419604", "chambre": null, "regime": "5\u00e8me R\u00e9publique", "legislature": "16", "secretariat": {"secretaire01": null, "secretaire02": null}}}