{"organe": {"@xmlns": "http://schemas.assemblee-nationale.fr/referentiel", "@xmlns:xsi": "http://www.w3.org/2001/XMLSchema-instance", "@xsi:type": "OrganeParlementaire_Type", "uid": "PO826607", "codeType": "MISINFO", "libelle": "Mission sur le financement public de l\u2019enseignement priv\u00e9 sous contrat", "libelleEdition": null, "libelleAbrege": "Financement public de l\u2019enseignement priv\u00e9 sous contrat", "libelleAbrev": "MIENSPRIVE", "viMoDe": {"dateDebut": "2023-07-20", "dateAgrement": null, "dateFin": "2024-04-02"}, "organeParent": "PO419604", "chambre": null, "regime": "5\u00e8me R\u00e9publique", "legislature": "16", "secretariat": {"secretaire01": null, "secretaire02": null}}}